{"cameraMode":{"drawMode":0,"name":"Shaded","section":"Shading Mode"},"sceneLighting":true,"audioPlay":false,"sceneViewState":{"m_AlwaysRefresh":false,"showFog":true,"showSkybox":true,"showFlares":true,"showImageEffects":true,"showParticleSystems":true,"showVisualEffectGraphs":true,"m_FxEnabled":true},"in2DMode":false,"pivot":{"x":53.87483215332031,"y":-103.06192016601563,"z":8.709386825561524},"rotation":{"x":0.3342910408973694,"y":0.5121145248413086,"z":-0.22452636063098908,"w":0.7590991854667664},"size":140.02232360839845,"orthographic":false}